skewt_fs/__init__.py
skewt_fs/distribution.py
skewt_fs-0.1.3.dist-info/METADATA
skewt_fs-0.1.3.dist-info/WHEEL
skewt_fs-0.1.3.dist-info/top_level.txt
skewt_fs-0.1.3.dist-info/RECORD
