Metadata-Version: 2.4
Name: skewt-fs
Version: 0.1.3
Summary: An implementation of the Fernandez-Steel skewed Student's t-distribution.
Author-email: Samarth P <samarthpardhi307@gmail.com>
Project-URL: Homepage, https://github.com/samarthpardhi/skewt_fs
Project-URL: Bug Tracker, https://github.com/samarthpardhi/skewt_fs/issues
Classifier: Programming Language :: Python :: 3
Classifier: License :: OSI Approved :: MIT License
Classifier: Operating System :: OS Independent
Requires-Python: >=3.8
Requires-Dist: numpy
Requires-Dist: scipy
